audio_soundwave_generator/__init__.py
audio_soundwave_generator-0.0.4.dist-info/LICENSE
audio_soundwave_generator-0.0.4.dist-info/METADATA
audio_soundwave_generator-0.0.4.dist-info/WHEEL
audio_soundwave_generator-0.0.4.dist-info/top_level.txt
audio_soundwave_generator-0.0.4.dist-info/RECORD
